odoo/addons/ssi_infrastructure/README.rst
odoo/addons/ssi_infrastructure/__init__.py
odoo/addons/ssi_infrastructure/__manifest__.py
odoo/addons/ssi_infrastructure/menu.xml
odoo/addons/ssi_infrastructure/models/__init__.py
odoo/addons/ssi_infrastructure/models/res_company.py
odoo/addons/ssi_infrastructure/models/res_config_settings.py
odoo/addons/ssi_infrastructure/security/ir_module_category_data.xml
odoo/addons/ssi_infrastructure/static/description/icon.png
odoo/addons/ssi_infrastructure/views/res_config_settings_views.xml
odoo14_addon_ssi_infrastructure-14.0.1.0.0.dist-info/METADATA
odoo14_addon_ssi_infrastructure-14.0.1.0.0.dist-info/WHEEL
odoo14_addon_ssi_infrastructure-14.0.1.0.0.dist-info/top_level.txt
odoo14_addon_ssi_infrastructure-14.0.1.0.0.dist-info/RECORD
